crawlab/__init__.py
crawlab/cli/__init__.py
crawlab/config/__init__.py
crawlab/constants/__init__.py
crawlab/core/__init__.py
crawlab/core/client.py
crawlab/core/config.py
crawlab/core/log.py
crawlab/core/request.py
crawlab/db/__init__.py
crawlab/db/es.py
crawlab/db/kafka.py
crawlab/db/mongo.py
crawlab/db/sql.py
crawlab/pipelines/__init__.py
crawlab/utils/__init__.py
crawlab/utils/config.py
crawlab/utils/data.py
crawlab/utils/scrapy.py
crawlab_sdk_ssl-0.0.6.dist-info/METADATA
crawlab_sdk_ssl-0.0.6.dist-info/WHEEL
crawlab_sdk_ssl-0.0.6.dist-info/entry_points.txt
crawlab_sdk_ssl-0.0.6.dist-info/top_level.txt
crawlab_sdk_ssl-0.0.6.dist-info/RECORD
