Metadata-Version: 2.1
Name: crawlab-sdk-ssl
Version: 0.0.6
Summary: Python SDK for Crawlab
Home-page: https://github.com/crawlab-team/crawlab-sdk
Author: tikazyq
Author-email: tikazyq@163.com
License: BSD-3-Clause
Platform: UNKNOWN
Classifier: Programming Language :: Python :: 3
Classifier: License :: OSI Approved :: BSD License
Classifier: Operating System :: OS Independent
Requires-Dist: click
Requires-Dist: requests
Requires-Dist: prettytable
Requires-Dist: scrapy
Requires-Dist: pymongo
Requires-Dist: pymysql
Requires-Dist: psycopg2-binary
Requires-Dist: kafka-python
Requires-Dist: elasticsearch
Requires-Dist: pathspec
